Netaxgen/__init__.py
Netaxgen/network.cpython-311-darwin.so
Netaxgen-0.1.1.dist-info/LICENSE.txt
Netaxgen-0.1.1.dist-info/METADATA
Netaxgen-0.1.1.dist-info/WHEEL
Netaxgen-0.1.1.dist-info/top_level.txt
Netaxgen-0.1.1.dist-info/RECORD
