Metadata-Version: 2.1
Name: Netaxgen
Version: 0.1.1
Summary: A package for generating network files
Author: Gongruihao
Author-email: 202031200039@mail.bnu.edu.cn
Classifier: Programming Language :: Python :: 3
Classifier: Programming Language :: Python :: 3.7
Classifier: Programming Language :: Python :: 3.8
Classifier: Programming Language :: Python :: 3.9
License-File: LICENSE.txt
